encdecpy/__init__.py
encdecpy/atbash.py
encdecpy/base64.py
encdecpy/caesar.py
encdecpy/rot13.py
encdecpy-0.1.dist-info/LICENSE
encdecpy-0.1.dist-info/METADATA
encdecpy-0.1.dist-info/WHEEL
encdecpy-0.1.dist-info/top_level.txt
encdecpy-0.1.dist-info/RECORD
